axe_core_python/__init__.py
axe_core_python/async_playwright.py
axe_core_python/axe.min.js
axe_core_python/base.py
axe_core_python/selenium.py
axe_core_python/sync_playwright.py
axe_core_python-0.1.0.dist-info/LICENSE
axe_core_python-0.1.0.dist-info/WHEEL
axe_core_python-0.1.0.dist-info/METADATA
axe_core_python-0.1.0.dist-info/RECORD
