Metadata-Version: 2.1
Name: axe-core-python
Version: 0.1.0
Summary: Automated web accessibility testing using axe-core engine.
Home-page: https://github.com/ruslan-rv-ua/axe-core-python
License: MIT
Keywords: accessibility,axe,axe-core,selenium,playwright
Author: Ruslan Iskov
Author-email: ruslan.rv.ua@gmail.com
Requires-Python: >=3.10,<4.0
Classifier: Development Status :: 5 - Production/Stable
Classifier: License :: OSI Approved :: MIT License
Classifier: Programming Language :: Python
Classifier: Programming Language :: Python :: 3
Classifier: Programming Language :: Python :: 3.10
Classifier: Topic :: Adaptive Technologies
Classifier: Topic :: Software Development
Classifier: Topic :: Software Development :: Quality Assurance
Classifier: Topic :: Software Development :: Testing
Project-URL: Documentation, https://ruslan-rv-ua.github.io/axe-core-python/
Project-URL: Repository, https://github.com/ruslan-rv-ua/axe-core-python
